bird_parser/__init__.py
bird_parser/main.py
bird_parser/output_schema.json
bird_parser/parse_bird_output.py
bird_parser/utils.py
bird_ospf_link_db_parser-1.1.3.dist-info/LICENSE.txt
bird_ospf_link_db_parser-1.1.3.dist-info/METADATA
bird_ospf_link_db_parser-1.1.3.dist-info/WHEEL
bird_ospf_link_db_parser-1.1.3.dist-info/entry_points.txt
bird_ospf_link_db_parser-1.1.3.dist-info/top_level.txt
bird_ospf_link_db_parser-1.1.3.dist-info/RECORD
