Metadata-Version: 2.1
Name: bird-ospf-link-db-parser
Version: 1.1.3
Summary: Parse the text output from the BIRD Routing Daemon's OSPF link database into machine readable JSON
Author-email: Andrew Dickinson <andrew.dickinson.0216@gmail.com>
License: MIT License
Project-URL: repository, https://github.com/Andrew-Dickinson/bird-ospf-link-db-parser
Classifier: License :: OSI Approved :: MIT License
Classifier: Programming Language :: Python :: 3
Classifier: Operating System :: OS Independent
License-File: LICENSE.txt
Requires-Dist: python-dotenv
Requires-Dist: pytz
Requires-Dist: python-dateutil
Requires-Dist: jsonschema
Provides-Extra: dev
Requires-Dist: build ; extra == 'dev'
Requires-Dist: twine ; extra == 'dev'
Provides-Extra: test
Requires-Dist: pytest (>=6) ; extra == 'test'
Requires-Dist: coverage ; extra == 'test'
Requires-Dist: freezegun ; extra == 'test'
